pycounts_zhy99/__init__.py
pycounts_zhy99/plotting.py
pycounts_zhy99/pycounts_zhy99.py
pycounts_zhy99-0.1.0.dist-info/LICENSE
pycounts_zhy99-0.1.0.dist-info/METADATA
pycounts_zhy99-0.1.0.dist-info/WHEEL
pycounts_zhy99-0.1.0.dist-info/RECORD
